codecapsule/__init__.py
codecapsule/__main__.py
codecapsule/core.py
codecapsule/version.py
codecapsule-1.0.5.dist-info/METADATA
codecapsule-1.0.5.dist-info/WHEEL
codecapsule-1.0.5.dist-info/entry_points.txt
codecapsule-1.0.5.dist-info/licenses/LICENSE
codecapsule-1.0.5.dist-info/RECORD
