Metadata-Version: 2.4
Name: codecapsule
Version: 1.0.5
Summary: Transform entire projects into portable JSON capsules for easy sharing and LLM processing
Project-URL: Homepage, https://github.com/joshschmelzle/codecapsule
Project-URL: Bug Tracker, https://github.com/joshschmelzle/codecapsule/issues
Author-email: Josh Schmelzle <josh@joshschmelzle.com>
License: BSD 3-Clause License
License-File: LICENSE
Classifier: License :: OSI Approved :: BSD License
Classifier: Operating System :: OS Independent
Classifier: Programming Language :: Python :: 3
Classifier: Programming Language :: Python :: 3.8
Classifier: Programming Language :: Python :: 3.9
Classifier: Programming Language :: Python :: 3.10
Classifier: Programming Language :: Python :: 3.11
Classifier: Programming Language :: Python :: 3.12
Classifier: Programming Language :: Python :: 3.13
Requires-Python: >=3.8
